cioppino.twothumbs-3.0.0-py3.9-nspkg.pth
cioppino/twothumbs/__init__.py
cioppino/twothumbs/configure.zcml
cioppino/twothumbs/event.py
cioppino/twothumbs/indexers.py
cioppino/twothumbs/interfaces.py
cioppino/twothumbs/rate.py
cioppino/twothumbs/rebuild_i18n.sh
cioppino/twothumbs/setuphandlers.py
cioppino/twothumbs/testing.py
cioppino/twothumbs/triggers_handlers.py
cioppino/twothumbs/browser/__init__.py
cioppino/twothumbs/browser/configure.zcml
cioppino/twothumbs/browser/like.py
cioppino/twothumbs/browser/images/thumbs-down-badge.png
cioppino/twothumbs/browser/images/thumbs-down-off.png
cioppino/twothumbs/browser/images/thumbs-down-on.png
cioppino/twothumbs/browser/images/thumbs-sprite.png
cioppino/twothumbs/browser/images/thumbs-up-badge.png
cioppino/twothumbs/browser/images/thumbs-up-off.png
cioppino/twothumbs/browser/images/thumbs-up-on.png
cioppino/twothumbs/browser/images/source/Thumbs.psd
cioppino/twothumbs/browser/javascripts/twothumbs.js
cioppino/twothumbs/browser/stylesheets/twothumbs.css
cioppino/twothumbs/browser/templates/login_to_rate.pt
cioppino/twothumbs/browser/templates/thumbs.pt
cioppino/twothumbs/locales/cioppino.twothumbs.pot
cioppino/twothumbs/locales/plone-custom.pot
cioppino/twothumbs/locales/plone.pot
cioppino/twothumbs/locales/ca/LC_MESSAGES/cioppino.twothumbs.mo
cioppino/twothumbs/locales/ca/LC_MESSAGES/cioppino.twothumbs.po
cioppino/twothumbs/locales/de/LC_MESSAGES/cioppino.twothumbs.mo
cioppino/twothumbs/locales/de/LC_MESSAGES/cioppino.twothumbs.po
cioppino/twothumbs/locales/en/LC_MESSAGES/cioppino.twothumbs.mo
cioppino/twothumbs/locales/en/LC_MESSAGES/cioppino.twothumbs.po
cioppino/twothumbs/locales/es/LC_MESSAGES/cioppino.twothumbs.mo
cioppino/twothumbs/locales/es/LC_MESSAGES/cioppino.twothumbs.po
cioppino/twothumbs/locales/fr/LC_MESSAGES/cioppino.twothumbs.mo
cioppino/twothumbs/locales/fr/LC_MESSAGES/cioppino.twothumbs.po
cioppino/twothumbs/locales/it/LC_MESSAGES/cioppino.twothumbs.mo
cioppino.twothumbs-3.0.0.dist-info/METADATA
cioppino.twothumbs-3.0.0.dist-info/WHEEL
cioppino.twothumbs-3.0.0.dist-info/entry_points.txt
cioppino.twothumbs-3.0.0.dist-info/namespace_packages.txt
cioppino.twothumbs-3.0.0.dist-info/top_level.txt
cioppino.twothumbs-3.0.0.dist-info/RECORD
